pyvalid/__accepts.py
pyvalid/__exceptions.py
pyvalid/__init__.py
pyvalid/__main__.py
pyvalid/__returns.py
pyvalid/switch.py
pyvalid/validators/__base.py
pyvalid/validators/__init__.py
pyvalid/validators/__iterable.py
pyvalid/validators/__number.py
pyvalid/validators/__string.py
pyvalid-1.0.4.dist-info/LICENSE
pyvalid-1.0.4.dist-info/METADATA
pyvalid-1.0.4.dist-info/WHEEL
pyvalid-1.0.4.dist-info/top_level.txt
pyvalid-1.0.4.dist-info/RECORD
